ANNOUNCE
ANNOUNCE-0.1.5
ChangeLog
MANIFEST.in
README
gsl-mode-0.1.el
setup.py
guppy/__init__.py
guppy.egg-info/PKG-INFO
guppy.egg-info/SOURCES.txt
guppy.egg-info/dependency_links.txt
guppy.egg-info/top_level.txt
guppy/doc/ProfileBrowser.html
guppy/doc/__init__.py
guppy/doc/docexample.html
guppy/doc/docexample.py
guppy/doc/gsl.html
guppy/doc/gslexample.html
guppy/doc/guppy.html
guppy/doc/heapy_RootState.html
guppy/doc/heapy_UniSet.html
guppy/doc/heapy_Use.html
guppy/doc/heapy_tutorial.html
guppy/doc/heapyc.html
guppy/doc/index.html
guppy/doc/pbscreen.jpg
guppy/doc/sets.html
guppy/doc/test_guppy.py
guppy/doc/test_heapy.py
guppy/doc/test_heapyc.py
guppy/etc/Cat.py
guppy/etc/Code.py
guppy/etc/Compat.py
guppy/etc/ExecfileWithModuleInfo.py
guppy/etc/FSA.py
guppy/etc/Glue.py
guppy/etc/Help.py
guppy/etc/IterPermute.py
guppy/etc/KanExtension.py
guppy/etc/KnuthBendix.py
guppy/etc/OutputHandling.py
guppy/etc/RE.py
guppy/etc/RE_Rect.py
guppy/etc/Unpack.py
guppy/etc/__init__.py
guppy/etc/cmd.py
guppy/etc/etc.py
guppy/etc/textView.py
guppy/etc/tkcursors.py
guppy/etc/xterm.py
guppy/gsl/Document.py
guppy/gsl/DottedTree.py
guppy/gsl/Exceptions.py
guppy/gsl/FileIO.py
guppy/gsl/Filer.py
guppy/gsl/Gsml.py
guppy/gsl/Help.py
guppy/gsl/Html.py
guppy/gsl/Latex.py
guppy/gsl/Main.py
guppy/gsl/SpecNodes.py
guppy/gsl/Tester.py
guppy/gsl/Text.py
guppy/gsl/XHTML.py
guppy/gsl/__init__.py
guppy/heapy/AbstractAlgebra.py
guppy/heapy/Classifiers.py
guppy/heapy/Console.py
guppy/heapy/Doc.py
guppy/heapy/ImpSet.py
guppy/heapy/Monitor.py
guppy/heapy/OutputHandling.py
guppy/heapy/Part.py
guppy/heapy/Path.py
guppy/heapy/Prof.py
guppy/heapy/RM.py
guppy/heapy/RefPat.py
guppy/heapy/Remote.py
guppy/heapy/RemoteConstants.py
guppy/heapy/Spec.py
guppy/heapy/Target.py
guppy/heapy/UniSet.py
guppy/heapy/Use.py
guppy/heapy/View.py
guppy/heapy/__init__.py
guppy/heapy/pbhelp.py
guppy/heapy/test/__init__.py
guppy/heapy/test/support.py
guppy/heapy/test/test_Classifiers.py
guppy/heapy/test/test_ER.py
guppy/heapy/test/test_OutputHandling.py
guppy/heapy/test/test_Part.py
guppy/heapy/test/test_Path.py
guppy/heapy/test/test_RefPat.py
