Metadata-Version: 1.0
Name: guppy
Version: 0.1.9
Summary: Guppy-PE -- A Python Programming Environment
Home-page: http://guppy-pe.sourceforge.net
Author: Sverker Nilsson
Author-email: sn@sncs.se
License: MIT
Platform: UNKNOWN
